Metadata-Version: 2.4
Name: x_make_yahw_x
Version: 12.0.1
Summary: Really simple 'Yet Another Hello World' package.
Author-email: RRGM of the Primus Pilus Night Watch AI Corporation <eye4357@outlook.com>
License-Expression: MIT
